burner/__main__.py
burner/client.py
burner/database.py
burner/exceptions.py
burner/resources/__init__.py
burner/resources/sms.db
burner/session.py
burner-0.8.1.dist-info/entry_points.txt
burner-0.8.1.dist-info/LICENSE
burner-0.8.1.dist-info/WHEEL
burner-0.8.1.dist-info/METADATA
burner-0.8.1.dist-info/RECORD
