Metadata-Version: 2.1
Name: burner
Version: 0.8.1
Summary: Script to interact with SimSMS's website.
Home-page: https://github.com/ramadan8/Burner
License: MIT
Keywords: phone,burner,sms,simsms
Author: Aidan
Author-email: ramadan8@riseup.net
Requires-Python: >=3.8,<4.0
Classifier: License :: OSI Approved :: MIT License
Classifier: Programming Language :: Python :: 3
Classifier: Programming Language :: Python :: 3.8
Classifier: Programming Language :: Python :: 3.9
Classifier: Programming Language :: Python :: 3.10
Classifier: Programming Language :: Python :: 3.11
Classifier: Programming Language :: Python :: 3.10
Classifier: Programming Language :: Python :: 3.11
Classifier: Programming Language :: Python :: 3.12
Classifier: Programming Language :: Python :: 3.8
Classifier: Programming Language :: Python :: 3.9
Classifier: Topic :: Communications :: Internet Phone
Requires-Dist: beautifulsoup4 (>=4.11.1,<5.0.0)
Requires-Dist: click (>=8.1.3,<9.0.0)
Requires-Dist: peewee (>=3.15.3,<4.0.0)
Requires-Dist: phonenumbers (>=8.12.57,<9.0.0)
Requires-Dist: requests (>=2.28.1,<3.0.0)
Project-URL: Repository, https://github.com/ramadan8/Burner
